chyp/__init__.py
chyp/__main__.py
chyp/graph.py
chyp/layout.py
chyp/matcher.py
chyp/parser.py
chyp/rewrite.py
chyp/rule.py
chyp/scraps.py
chyp/state.py
chyp/term.py
chyp/gui/__init__.py
chyp/gui/app.py
chyp/gui/codeview.py
chyp/gui/colors.py
chyp/gui/completion.py
chyp/gui/document.py
chyp/gui/editor.py
chyp/gui/errorlist.py
chyp/gui/graphscene.py
chyp/gui/graphview.py
chyp/gui/highlighter.py
chyp/gui/mainwindow.py
chyp/tactic/__init__.py
chyp/tactic/ruletac.py
chyp/tactic/simptac.py
chyp-0.5.2.dist-info/LICENSE
chyp-0.5.2.dist-info/METADATA
chyp-0.5.2.dist-info/WHEEL
chyp-0.5.2.dist-info/entry_points.txt
chyp-0.5.2.dist-info/top_level.txt
chyp-0.5.2.dist-info/RECORD
