Metadata-Version: 2.1
Name: chyp
Version: 0.5.2
Summary: An interactive theorem prover for string diagrams
Home-page: https://github.com/akissinger/chyp
Author: Aleks Kissinger
Author-email: aleks0@gmail.com
License: Apache2
Project-URL: Bug Tracker, https://github.com/akissinger/chyp/issues
Classifier: Programming Language :: Python :: 3
Classifier: License :: OSI Approved :: Apache Software License
Classifier: Operating System :: OS Independent
Requires-Python: >=3.7
License-File: LICENSE
Requires-Dist: PySide6 (>=6.4.3)
Requires-Dist: lark (>=1.1.5)
Requires-Dist: cvxpy (>=1.3.1)
